pycounts_hmyn/__init__.py
pycounts_hmyn/plotting.py
pycounts_hmyn/pycounts_hmyn.py
pycounts_hmyn-0.1.0.dist-info/LICENSE
pycounts_hmyn-0.1.0.dist-info/WHEEL
pycounts_hmyn-0.1.0.dist-info/METADATA
pycounts_hmyn-0.1.0.dist-info/RECORD
